WangfengShiwen110/README.md
WangfengShiwen110/__init__.py
WangfengShiwen110/__main__.py
WangfengShiwen110/file.epub
WangfengShiwen110/index.html
WangfengShiwen110/css/__init__.py
WangfengShiwen110/css/annotations.css
WangfengShiwen110/css/main.css
WangfengShiwen110/css/normalize.css
WangfengShiwen110/css/popup.css
WangfengShiwen110/font/__init__.py
WangfengShiwen110/font/fontello.eot
WangfengShiwen110/font/fontello.svg
WangfengShiwen110/font/fontello.ttf
WangfengShiwen110/font/fontello.woff
WangfengShiwen110/img/__init__.py
WangfengShiwen110/img/annotator-glyph-sprite.png
WangfengShiwen110/img/annotator-icon-sprite.png
WangfengShiwen110/img/apple-touch-icon.png
WangfengShiwen110/img/cancelfullscreen.png
WangfengShiwen110/img/close.png
WangfengShiwen110/img/fullscreen.png
WangfengShiwen110/img/loader.gif
WangfengShiwen110/img/menu-icon.png
WangfengShiwen110/img/save.png
WangfengShiwen110/img/saved.png
WangfengShiwen110/img/settings-s.png
WangfengShiwen110/img/settings.png
WangfengShiwen110/img/star.png
WangfengShiwen110/js/__init__.py
WangfengShiwen110/js/epub.js
WangfengShiwen110/js/epub.min.js
WangfengShiwen110/js/epub.min.map
WangfengShiwen110/js/hooks.min.js
WangfengShiwen110/js/hooks.min.map
WangfengShiwen110/js/reader.js
WangfengShiwen110/js/reader.js.map
WangfengShiwen110/js/reader.min.js
WangfengShiwen110/js/reader.min.map
WangfengShiwen110/js/hooks/__init__.py
WangfengShiwen110/js/hooks/extensions/__init__.py
WangfengShiwen110/js/hooks/extensions/highlight.js
WangfengShiwen110/js/libs/__init__.py
WangfengShiwen110/js/libs/jquery.min.js
WangfengShiwen110/js/libs/localforage.min.js
WangfengShiwen110/js/libs/screenfull.js
WangfengShiwen110/js/libs/screenfull.min.js
WangfengShiwen110/js/libs/zip.min.js
WangfengShiwen110/js/plugins/__init__.py
WangfengShiwen110/js/plugins/hypothesis.js
WangfengShiwen110/js/plugins/search.js
wangfeng_shiwen_1_10-2024.3.5.0.dist-info/METADATA
wangfeng_shiwen_1_10-2024.3.5.0.dist-info/WHEEL
wangfeng_shiwen_1_10-2024.3.5.0.dist-info/entry_points.txt
wangfeng_shiwen_1_10-2024.3.5.0.dist-info/top_level.txt
wangfeng_shiwen_1_10-2024.3.5.0.dist-info/RECORD
